students/__init__.py
students/admin.py
students/apps.py
students/models.py
students/tests.py
students/views.py
students/migrations/0001_initial.py
students/migrations/0002_auto_20200608_0821.py
students/migrations/0003_auto_20200609_1817.py
students/migrations/0004_auto_20200609_2024.py
students/migrations/0005_auto_20200609_2026.py
students/migrations/0006_auto_20200610_1504.py
students/migrations/0007_student_gender.py
students/migrations/0008_auto_20200610_1641.py
students/migrations/0009_auto_20200612_1953.py
students/migrations/0010_auto_20200612_2233.py
students/migrations/0011_auto_20200613_1111.py
students/migrations/0012_fees_update.py
students/migrations/0013_auto_20200614_1011.py
students/migrations/0014_auto_20200614_1012.py
students/migrations/0015_auto_20200614_1013.py
students/migrations/0016_auto_20200614_1014.py
students/migrations/0017_payment_name_of_month.py
students/migrations/0018_remove_payment_name_of_month.py
students/migrations/0019_auto_20200614_1027.py
students/migrations/0020_remove_enrollment_fees_update.py
students/migrations/__init__.py
Student_Management-2.0.5.dist-info/LICENSE
Student_Management-2.0.5.dist-info/METADATA
Student_Management-2.0.5.dist-info/WHEEL
Student_Management-2.0.5.dist-info/top_level.txt
Student_Management-2.0.5.dist-info/RECORD
